chellow/__init__.py
chellow/api.py
chellow/bank_holidays.py
chellow/dloads.py
chellow/edi_lib.py
chellow/fake_batch_updater.py
chellow/general_import.py
chellow/models.py
chellow/proxy.py
chellow/rate_server.py
chellow/rrun.py
chellow/testing.py
chellow/utils.py
chellow/views.py
chellow/e/__init__.py
chellow/e/aahedc.py
chellow/e/bill_importer.py
chellow/e/bmarketidx.py
chellow/e/bsuos.py
chellow/e/ccl.py
chellow/e/cfd.py
chellow/e/computer.py
chellow/e/dno_rate_parser.py
chellow/e/duos.py
chellow/e/elexon.py
chellow/e/energy_management.py
chellow/e/glossary.py
chellow/e/hh_importer.py
chellow/e/hh_parser_bg_csv.py
chellow/e/hh_parser_df2.py
chellow/e/hh_parser_edf_csv.py
chellow/e/hh_parser_schneider_csv.py
chellow/e/hh_parser_schneider_xlsx.py
chellow/e/hh_parser_simple_csv.py
chellow/e/hh_parser_vital_xlsx.py
chellow/e/isd.py
chellow/e/issues.py
chellow/e/lafs.py
chellow/e/lcc.py
chellow/e/mdd_importer.py
chellow/e/neso.py
chellow/e/rab.py
chellow/e/rcrc.py
chellow/e/ro.py
chellow/e/scenario.py
chellow/e/system_price.py
chellow/e/tlms.py
chellow/e/tnuos.py
chellow/e/triad.py
chellow/e/views.py
chellow/e/bill_parsers/__init__.py
chellow/e/bill_parsers/activity_mop_stark_xlsx.py
chellow/e/bill_parsers/amr_dc_stark_xlsx.py
chellow/e/bill_parsers/annual_mop_stark_xlsx.py
chellow/e/bill_parsers/bgb_edi.py
chellow/e/bill_parsers/csv.py
chellow/e/bill_parsers/drax_edi.py
chellow/e/bill_parsers/edf_export_xlsx.py
chellow/e/bill_parsers/engie_edi.py
chellow/e/bill_parsers/engie_export_xlsx.py
chellow/e/bill_parsers/engie_xls.py
chellow/e/bill_parsers/engie_xlsx.py
chellow/e/bill_parsers/gdf_csv.py
chellow/e/bill_parsers/haven_csv.py
chellow/e/bill_parsers/haven_edi.py
chellow/e/bill_parsers/haven_edi_tprs.py
chellow/e/bill_parsers/mm.py
chellow/e/bill_parsers/nonsettlement_dc_stark_xlsx.py
chellow/e/bill_parsers/settlement_dc_stark_xlsx.py
chellow/e/bill_parsers/sse_edi.py
chellow/e/bill_parsers/sww_xls.py
chellow/gas/bill_import.py
chellow/gas/bill_parser_bgs_xlsx.py
chellow-1769782225.0.0.dist-info/METADATA
chellow-1769782225.0.0.dist-info/WHEEL
chellow-1769782225.0.0.dist-info/RECORD
