Metadata-Version: 2.4
Name: chellow
Version: 1769782225.0.0
Summary: Web Application for checking UK energy bills.
Project-URL: Homepage, https://github.com/WessexWater/chellow
Classifier: License :: OSI Approved :: GNU General Public License v3 (GPLv3)
Classifier: Operating System :: OS Independent
Classifier: Programming Language :: Python :: 3
Requires-Python: >=3.11
Requires-Dist: flask-restx==1.3.2
Requires-Dist: flask==3.1.2
Requires-Dist: jsonschema==4.26.0
Requires-Dist: markdown-it-py==4.0.0
Requires-Dist: odio==0.0.23
Requires-Dist: openpyxl==3.1.5
Requires-Dist: paramiko==4.0.0
Requires-Dist: pg8000==1.31.5
Requires-Dist: pip>=9.0.1
Requires-Dist: psutil==7.1.1
Requires-Dist: pympler==1.1
Requires-Dist: pypdf==6.6.2
Requires-Dist: python-dateutil==2.8.2
Requires-Dist: pytz==2025.2
Requires-Dist: requests==2.32.5
Requires-Dist: sqlalchemy==2.0.45
Requires-Dist: waitress==3.0.2
Requires-Dist: xlrd==2.0.2
Requires-Dist: zish==0.1.12
